{
  "animateLoading": true,
  "borderRadius": "{{appsmith.theme.borderRadius.appBorderRadius}}",
  "bottomRow": 6,
  "boxShadow": "none",
  "buttonColor": "#22c55e",
  "buttonVariant": "PRIMARY",
  "dynamicBindingPathList": [
    {
      "key": "borderRadius"
    }
  ],
  "dynamicPropertyPathList": [
    {
      "key": "onClick"
    }
  ],
  "dynamicTriggerPathList": [
    {
      "key": "onClick"
    }
  ],
  "iconName": "refresh",
  "isDisabled": false,
  "isLoading": false,
  "isVisible": true,
  "key": "jws2wt4o7t",
  "leftColumn": 0,
  "minWidth": 50,
  "mobileBottomRow": 4,
  "mobileLeftColumn": 0,
  "mobileRightColumn": 4,
  "mobileTopRow": 0,
  "needsErrorInfo": false,
  "onClick": "{{calculo_do_google.run().then(() => {\n  pedidos_e_saidas_do_dia.run();\n  dmaplicativo_prod_rotas_otimiz.run();\n  ultimo_pedido_da_saida.run();\n  rotas_bi_motoboy.run();\n  showAlert('Atualizado com sucesso1 Agurde os dados serão carredos na pagina!', 'success');\n});}}",
  "parentColumnSpace": 20.25,
  "parentId": "0",
  "parentRowSpace": 10,
  "renderMode": "CANVAS",
  "responsiveBehavior": "hug",
  "rightColumn": 3,
  "topRow": 2,
  "type": "ICON_BUTTON_WIDGET",
  "version": 1,
  "widgetId": "zj3cvlk52c",
  "widgetName": "IconButton1"
}